pspoly/__init__.py
pspoly/Igor/PS_POLY_5_3_24.ipf
pspoly/Python/filters.py
pspoly/Python/length.py
pspoly/Python/pspoly.py
pspoly/Python/utilities.py
pspoly-0.3.0.dist-info/METADATA
pspoly-0.3.0.dist-info/WHEEL
pspoly-0.3.0.dist-info/licenses/LICENSE
pspoly-0.3.0.dist-info/RECORD
