Metadata-Version: 2.3
Name: pspoly
Version: 0.3.0
Summary: Polymer Image Analysis and Shape Categorization
Project-URL: Homepage, https://kinggm.mufaculty.umsystem.edu
Project-URL: Repository, https://github.com/KingGavinM/PS-Poly
Author: Elizabeth Conley, Katherine Schaefer
Author-email: Harrison Davison <hcdq9t@umsystem.edu>, Gavin King <kinggm@missouri.edu>
Maintainer-email: Harrison Davison <hcdq9t@umsystem.edu>
License: Attribution-NonCommercial 4.0 International
License-File: LICENSE
Keywords: AFM,atomic force microscopy,image analysis,persistence length,polymer
Classifier: Programming Language :: Python
Requires-Python: >=3.8
Requires-Dist: matplotlib>=3.7.5
Requires-Dist: numpy>=1.24.4
Requires-Dist: scikit-image>=0.21.0
Requires-Dist: scipy>=1.10.1
